{
    "prop57":[
    {
        "propid": 57,
        "id": 0,
        "slideid": "prop570",
        "maintext": "Do convicted non-violent felons deserve a break?",
        "lefttext": "Yes! ",
        "righttext": "No, crime desrerves punishment.",
        "leftslide": "prop571",
        "leftid": 1,
        "rightslide": "prop571",
        "rightid": 1,
        "leftpoints": 1,
        "rightpoints": -1
    },
    {
        "propid": 57,
        "id": 1,
        "slideid": "prop571",
        "maintext": "Have you or a close family member been in jail for a non-violent crime",
        "lefttext": "Yes <<Sigh>>",
        "righttext": "No, never.",
        "leftslide": "prop572",
        "leftid": 2,
        "rightslide": "prop572",
        "rightid": 2,
        "leftpoints": 1,
        "rightpoints": -1
    },
    {
        "propid": 57,
        "id": 2,
        "slideid": "prop572",
        "maintext": "Do longer jail sentences prevent worse cirmes?",
        "lefttext": "Yes, and it keeps society in order.",
        "righttext": "Nope, sentencing is not crime prevention.",
        "leftslide": "prop573",
        "leftid": 3,
        "rightslide": "prop573",
        "rightid": 3,
        "leftpoints": -1,
        "rightpoints": 1
    },
    {
        "propid": 57,
        "id": 3,
        "slideid": "prop573",
        "maintext": "Do you think good behavior and education are good reasons to be released from prison early, or do you think crimes will be committed after release?",
        "lefttext": "Rehabilitation should be rewarded.",
        "righttext": "More crimes will be committed by ex-con.",
        "leftslide": "prop574",
        "leftid": 4,
        "rightslide": "prop574",
        "rightid": 4,
        "leftpoints": -1,
        "rightpoints": 1
    },
    {
        "propid": 57,
        "id": 4,
        "slideid": "prop574",
        "maintext": "So the feds say we have to reducethe  prison popultation here. Is releasing non-violent offenders a good starting place?",
        "lefttext": "Makes sense.",
        "righttext": "Nope, sets a bad precedent.",
        "leftslide": "prop575",
        "leftid": 5,
        "rightslide": "prop575",
        "rightid": 5,
        "leftpoints": 1,
        "rightpoints": -1
    },
    {
        "propid": 57,
        "id": 5,
        "slideid": "prop575",
        "maintext": "Do you think a prosecutor or a judge should decide whether a youth should be tried as an adult?",
        "lefttext": "Judge.",
        "righttext": "Prosecutor.",
        "leftslide": "prop576",
        "leftid": 6,
        "rightslide": "prop576",
        "rightid": 6,
        "leftpoints": 1,
        "rightpoints": -1
    },
    {
        "propid": 57,
        "id": 6,
        "slideid": "prop576",
        "maintext": "If passed, 7,000 inmates would be eligible for immediate release. How does that sit with you?",
        "lefttext": "Sounds like freedom for many inmates and families.",
        "righttext": "Sounds bad/scary.",
        "leftslide": "prop577",
        "leftid": 7,
        "rightslide": "prop577",
        "rightid": 7,
        "leftpoints": 1,
        "rightpoints": -1
    },
    {
        "propid": 57,
        "id": 7,
        "slideid": "prop577",
        "maintext": "You may want to hold off on this initiative and keep prisoners where they are. ",
        "subtext": "Crime deserves punishment!",
        "leftslide": "resources",
        "leftid": -1,
        "rightslide": "resources",
        "rightid": -1,
        "leftpoints": 0,
        "rightpoints": 0,
        "victoryslide": true,
        "victorycond": "oppose",
        "special": "victory"
    },
    {
        "propid": 57,
        "id": 7,
        "slideid": "prop578",
        "maintext": "Ding ding! You support a win for prison reforms!",
        "subtext": "About time.",
        "leftslide": "resources",
        "leftid": -1,
        "rightslide": "resources",
        "rightid": -1,
        "leftpoints": 0,
        "rightpoints": 0,
        "victoryslide": true,
        "victorycond": "support",
        "special": "victory"
    },
    {
        "propid": 57,
        "id": 7,
        "slideid": "prop579",
        "maintext": "Your thoughts on this prop are locked up. ",
        "subtext": "Maybe I need to think about this.",
        "leftslide": "resources",
        "leftid": -1,
        "rightslide": "resources",
        "rightid": -1,
        "leftpoints": 0,
        "rightpoints": 0,
        "victoryslide": true,
        "victorycond": "default",
        "special": "victory"
    }
]
}